example_package_nqtuan/__init__.py
example_package_nqtuan/example.py
example_package_nqtuan-2.2.2.dist-info/METADATA
example_package_nqtuan-2.2.2.dist-info/WHEEL
example_package_nqtuan-2.2.2.dist-info/licenses/LICENSE
example_package_nqtuan-2.2.2.dist-info/RECORD
