Metadata-Version: 2.1
Name: example_package_nqtuan
Version: 2.2.2
Summary: A small example package
Project-URL: Homepage, https://bitbucket.org/hudsonglobalteam/tuan-test-python-packaging
Project-URL: Bug Tracker, https://bitbucket.org/hudsonglobalteam/tuan-test-python-packaging/issues
Author-email: "Tuan Nguyen Quoc(Aaron)" <quoctuanb6@gmail.com>
License-File: LICENSE
Classifier: License :: OSI Approved :: MIT License
Classifier: Operating System :: OS Independent
Classifier: Programming Language :: Python :: 3
Requires-Python: >=3.7
